<?xml version="1.0" encoding="UTF-8" ?>
<?xml-stylesheet  type="text/css" href="BookInfo.css"?>
<Book>
    <BookDetail>
        <TitleDetail>
            <Title>Head First Java, 2nd Edition</Title> by
            <Authors>Kathy Sierra, Bert Bates</Authors>
            <EditionInfo>PaperBack</EditionInfo>
            <PrintDate> Feb 9, 2005</PrintDate>
        </TitleDetail>
        <Price>
            New Price: <NewPrice>$29.67</NewPrice>
            Old Price: <OldPrice>$18.96</OldPrice>
        </Price>
        <OrderInfo>Get it by
            <GetDate>Tuesday,Feb, 27</GetDate>,if you order in the next
            <Hours>57 hours and</Hours>
            <Minutes>43 minutes</Minutes>
        </OrderInfo>
        <Edition>Other Editions:
            <EditionType>PaperBack, Digital</EditionType>
        </Edition>
    </BookDetail>

    <BookDetail>
        <TitleDetail>
            <Title>SCJP Sun Certified Programmer for Java 5 Study Guide (Exam 310-055) </Title> by
            <Authors>Katherine Sierra, Bert Bates</Authors>
            <EditionInfo>PaperBack</EditionInfo>
            <PrintDate> Dec 21, 2005</PrintDate>
        </TitleDetail>
        <Price>
            New Price: <NewPrice>$32.99</NewPrice>
            Old Price: <OldPrice>$30.87</OldPrice>
        </Price>
        <OrderInfo>Get it by
            <GetDate>Tuesday,Feb, 27</GetDate>,if you order in the next
            <Hours>37 hours and</Hours>
            <Minutes>47 minutes</Minutes>
        </OrderInfo>
        <Edition>Other Editions:
            <EditionType>PaperBack, Digital</EditionType>
        </Edition>
    </BookDetail>
</Book>